aiochclient/__init__.py
aiochclient/client.py
aiochclient/exceptions.py
aiochclient/records.py
aiochclient/types.py
aiochclient-0.0.4.dist-info/METADATA
aiochclient-0.0.4.dist-info/RECORD
aiochclient-0.0.4.dist-info/WHEEL
aiochclient-0.0.4.dist-info/top_level.txt
