Metadata-Version: 2.1
Name: aiochclient
Version: 0.0.4
Summary: Async http clickhouse client for python 3.6+
Home-page: https://github.com/maximdanilchenko/aiochclient
Author: Danilchenko Maksim
Author-email: dmax.dev@gmail.com
License: MIT
Keywords: clickhouse async python aiohttp
Platform: UNKNOWN
Classifier: Development Status :: 3 - Alpha
Classifier: Intended Audience :: Developers
Classifier: License :: OSI Approved :: MIT License
Classifier: Natural Language :: English
Classifier: Programming Language :: Python :: 3.5
Classifier: Programming Language :: Python :: 3.6
Classifier: Programming Language :: Python :: 3.7
Requires-Dist: aiohttp (<=3.4.4)
